kermac/__init__.py
kermac/build_a_kernel.py
kermac/cdist.py
kermac/cdist_grad.py
kermac/common.py
kermac/linalg/__init__.py
kermac/linalg/cholesky.py
kermac/linalg/common.py
kermac/linalg/lu_decomposition.py
kermac/linalg/syevd.py
kermac/module_cache/function_db_key.py
kermac/module_cache/function_db_value.py
kermac/module_cache/module_cache.py
kermac/module_cache/paths.py
include/build_a_kernel.cuh
include/kermac.cuh
include/kermac_internal_common.cuh
include/p_norm_gradient.cuh
thirdparty/cutlass/LICENSE.txt
thirdparty/cutlass/include/cute/config.hpp
thirdparty/cutlass/include/cute/int_tuple.hpp
thirdparty/cutlass/include/cute/layout.hpp
thirdparty/cutlass/include/cute/layout_composed.hpp
thirdparty/cutlass/include/cute/pointer.hpp
thirdparty/cutlass/include/cute/pointer_base.hpp
thirdparty/cutlass/include/cute/pointer_flagged.hpp
thirdparty/cutlass/include/cute/pointer_sparse.hpp
thirdparty/cutlass/include/cute/pointer_swizzle.hpp
thirdparty/cutlass/include/cute/stride.hpp
thirdparty/cutlass/include/cute/swizzle.hpp
thirdparty/cutlass/include/cute/swizzle_layout.hpp
thirdparty/cutlass/include/cute/tensor.hpp
thirdparty/cutlass/include/cute/tensor_impl.hpp
thirdparty/cutlass/include/cute/tensor_predicate.hpp
thirdparty/cutlass/include/cute/tensor_zip.hpp
thirdparty/cutlass/include/cute/underscore.hpp
thirdparty/cutlass/include/cute/algorithm/axpby.hpp
thirdparty/cutlass/include/cute/algorithm/clear.hpp
thirdparty/cutlass/include/cute/algorithm/cooperative_copy.hpp
thirdparty/cutlass/include/cute/algorithm/cooperative_gemm.hpp
thirdparty/cutlass/include/cute/algorithm/copy.hpp
thirdparty/cutlass/include/cute/algorithm/fill.hpp
thirdparty/cutlass/include/cute/algorithm/functional.hpp
thirdparty/cutlass/include/cute/algorithm/gemm.hpp
thirdparty/cutlass/include/cute/algorithm/prefer.hpp
thirdparty/cutlass/include/cute/algorithm/prefetch.hpp
thirdparty/cutlass/include/cute/algorithm/tensor_algorithms.hpp
thirdparty/cutlass/include/cute/algorithm/tuple_algorithms.hpp
kermac-0.1.4.dist-info/METADATA
kermac-0.1.4.dist-info/WHEEL
kermac-0.1.4.dist-info/licenses/LICENSE
kermac-0.1.4.dist-info/RECORD
