Metadata-Version: 2.4
Name: kermac
Version: 0.1.4
Summary: Pytorch routines for (Ker)nel (Mac)hines
Project-URL: Homepage, https://github.com/Kernel-Machines/kermac
Project-URL: Repository, https://github.com/Kernel-Machines/kermac.git
Author-email: Kernel Machines <kernel_machines@pm.me>
License: MIT
License-File: LICENSE
Requires-Python: >=3.8
Requires-Dist: cuda-pathfinder>=1.3
Requires-Dist: numpy>=1.21
Requires-Dist: platformdirs>=3.0
Requires-Dist: torch>=2.0
Provides-Extra: cu11
Requires-Dist: cuda-core[cu11]>=0.1; extra == 'cu11'
Provides-Extra: cu12
Requires-Dist: cuda-core[cu12]>=0.1; extra == 'cu12'
Provides-Extra: cu13
Requires-Dist: cuda-core[cu13]>=0.1; extra == 'cu13'
